notebook2script-0.2.1.dist-info/LICENSE
notebook2script-0.2.1.dist-info/top_level.txt
notebook2script-0.2.1.dist-info/entry_points.txt
notebook2script-0.2.1.dist-info/WHEEL
notebook2script-0.2.1.dist-info/METADATA
notebook2script/style.yapf
notebook2script/pointless.py
notebook2script/__init__.py
notebook2script/isort.cfg
notebook2script/py.typed
notebook2script/__main__.py
notebook2script/pointless_checker/__init__.py
notebook2script/pointless_checker/base.py
notebook2script-0.2.1.dist-info/RECORD
