Metadata-Version: 2.1
Name: notebook2script
Version: 0.2.1
Summary: Convert Jupyter Notebooks to Python Scripts.
Author-email: Dominic Davis-Foster <dominic@davis-foster.co.uk>
License: GPL-2.0-only
Keywords: converter,jupyter-notebook,utility
Home-page: https://github.com/PyMassSpec/notebook2script
Project-URL: Issue Tracker, https://github.com/PyMassSpec/notebook2script/issues
Project-URL: Source Code, https://github.com/PyMassSpec/notebook2script
Project-URL: Documentation, https://notebook2script.readthedocs.io/en/latest
Platform: Windows
Platform: macOS
Platform: Linux
Classifier: Development Status :: 4 - Beta
Classifier: Environment :: Console
Classifier: Intended Audience :: Developers
Classifier: Intended Audience :: End Users/Desktop
Classifier: License :: OSI Approved :: GNU General Public License v2 (GPLv2)
Classifier: Operating System :: OS Independent
Classifier: Operating System :: POSIX :: Linux
Classifier: Programming Language :: Python
Classifier: Programming Language :: Python :: 3 :: Only
Classifier: Programming Language :: Python :: 3.6
Classifier: Programming Language :: Python :: 3.7
Classifier: Programming Language :: Python :: 3.8
Classifier: Programming Language :: Python :: 3.9
Classifier: Programming Language :: Python :: Implementation :: CPython
Classifier: Topic :: Software Development
Classifier: Topic :: Utilities
Classifier: Typing :: Typed
Requires-Python: >=3.6
Requires-Dist: astroid<=2.5,>=2.4.0
Requires-Dist: click>=7.1.2
Requires-Dist: consolekit>=0.6.0
Requires-Dist: domdf-python-tools>=2.8.1
Requires-Dist: ipython>=7.14.0
Requires-Dist: isort>=5.5.2
Requires-Dist: nbconvert>=5.6.1
Requires-Dist: pre-commit-hooks>=3.3.0
Requires-Dist: pylint>=2.5.2
Requires-Dist: yapf-isort>=0.5.5
